{
    "quay_cranes": [
        {
            "idx": "QC1",
            "missions": {
                "M1": {
                    "idx": "M1",
                    "quay_crane_id": "QC1",
                    "yard_block_loc": [
                        "B1",
                        9,
                        6
                    ],
                    "yard_crane_process_time": 30.75586224017716,
                    "locked": true,
                    "release_time": 0,
                    "vehicle_speed": 1.435,
                    "station_process_time": 143.97971514993878,
                    "intersection_process_time": 41.08830656135419
                },
                "M2": {
                    "idx": "M2",
                    "quay_crane_id": "QC1",
                    "yard_block_loc": [
                        "A1",
                        23,
                        3
                    ],
                    "yard_crane_process_time": 26.376538421932388,
                    "locked": true,
                    "release_time": 120,
                    "vehicle_speed": 1.435,
                    "station_process_time": 118.29987206773448,
                    "intersection_process_time": 34.06945114062176
                },
                "M3": {
                    "idx": "M3",
                    "quay_crane_id": "QC1",
                    "yard_block_loc": [
                        "A4",
                        24,
                        6
                    ],
                    "yard_crane_process_time": 27.353106133153506,
                    "locked": true,
                    "release_time": 240,
                    "vehicle_speed": 1.435,
                    "station_process_time": 90.84930874160025,
                    "intersection_process_time": 30.44416709215945
                },
                "M4": {
                    "idx": "M4",
                    "quay_crane_id": "QC1",
                    "yard_block_loc": [
                        "A1",
                        16,
                        7
                    ],
                    "yard_crane_process_time": 30.942283585397696,
                    "locked": true,
                    "release_time": 360,
                    "vehicle_speed": 1.435,
                    "station_process_time": 144.70061170339736,
                    "intersection_process_time": 23.31348276411553
                },
                "M5": {
                    "idx": "M5",
                    "quay_crane_id": "QC1",
                    "yard_block_loc": [
                        "B2",
                        11,
                        4
                    ],
                    "yard_crane_process_time": 32.739918341866854,
                    "locked": true,
                    "release_time": 480,
                    "vehicle_speed": 1.435,
                    "station_process_time": 111.5793235627956,
                    "intersection_process_time": 52.98177558174792
                },
                "M6": {
                    "idx": "M6",
                    "quay_crane_id": "QC1",
                    "yard_block_loc": [
                        "B2",
                        20,
                        6
                    ],
                    "yard_crane_process_time": 34.19387015004976,
                    "locked": true,
                    "release_time": 600,
                    "vehicle_speed": 1.435,
                    "station_process_time": 94.91471449586545,
                    "intersection_process_time": 57.151744804033925
                },
                "M7": {
                    "idx": "M7",
                    "quay_crane_id": "QC1",
                    "yard_block_loc": [
                        "B1",
                        7,
                        1
                    ],
                    "yard_crane_process_time": 32.18171621404611,
                    "locked": true,
                    "release_time": 720,
                    "vehicle_speed": 1.435,
                    "station_process_time": 111.69037547967397,
                    "intersection_process_time": 43.2090914171864
                },
                "M8": {
                    "idx": "M8",
                    "quay_crane_id": "QC1",
                    "yard_block_loc": [
                        "A1",
                        21,
                        0
                    ],
                    "yard_crane_process_time": 31.56724222247243,
                    "locked": true,
                    "release_time": 840,
                    "vehicle_speed": 1.435,
                    "station_process_time": 105.7963764050877,
                    "intersection_process_time": 54.7372077705298
                },
                "M9": {
                    "idx": "M9",
                    "quay_crane_id": "QC1",
                    "yard_block_loc": [
                        "B1",
                        24,
                        2
                    ],
                    "yard_crane_process_time": 27.370042006712797,
                    "locked": true,
                    "release_time": 960,
                    "vehicle_speed": 1.435,
                    "station_process_time": 147.9277341334743,
                    "intersection_process_time": 44.91061372935514
                },
                "M10": {
                    "idx": "M10",
                    "quay_crane_id": "QC1",
                    "yard_block_loc": [
                        "C4",
                        9,
                        6
                    ],
                    "yard_crane_process_time": 30.587111771896563,
                    "locked": true,
                    "release_time": 1080,
                    "vehicle_speed": 1.435,
                    "station_process_time": 111.51551750786003,
                    "intersection_process_time": 26.584906326423045
                },
                "M11": {
                    "idx": "M11",
                    "quay_crane_id": "QC1",
                    "yard_block_loc": [
                        "A1",
                        1,
                        6
                    ],
                    "yard_crane_process_time": 28.28277894038776,
                    "locked": true,
                    "release_time": 1200,
                    "vehicle_speed": 1.435,
                    "station_process_time": 94.45987759589795,
                    "intersection_process_time": 31.545709025952753
                },
                "M12": {
                    "idx": "M12",
                    "quay_crane_id": "QC1",
                    "yard_block_loc": [
                        "B2",
                        3,
                        5
                    ],
                    "yard_crane_process_time": 31.343822200989308,
                    "locked": true,
                    "release_time": 1320,
                    "vehicle_speed": 1.435,
                    "station_process_time": 146.21799538046298,
                    "intersection_process_time": 54.50772967690235
                },
                "M13": {
                    "idx": "M13",
                    "quay_crane_id": "QC1",
                    "yard_block_loc": [
                        "A3",
                        19,
                        3
                    ],
                    "yard_crane_process_time": 31.48535505159804,
                    "locked": true,
                    "release_time": 1440,
                    "vehicle_speed": 1.435,
                    "station_process_time": 98.04060723336666,
                    "intersection_process_time": 34.457767016334174
                },
                "M14": {
                    "idx": "M14",
                    "quay_crane_id": "QC1",
                    "yard_block_loc": [
                        "A4",
                        16,
                        1
                    ],
                    "yard_crane_process_time": 26.737580868739624,
                    "locked": true,
                    "release_time": 1560,
                    "vehicle_speed": 1.435,
                    "station_process_time": 96.95130915583182,
                    "intersection_process_time": 28.495201281826397
                },
                "M15": {
                    "idx": "M15",
                    "quay_crane_id": "QC1",
                    "yard_block_loc": [
                        "B1",
                        16,
                        2
                    ],
                    "yard_crane_process_time": 25.823684678564412,
                    "locked": true,
                    "release_time": 1680,
                    "vehicle_speed": 1.435,
                    "station_process_time": 104.68862723819805,
                    "intersection_process_time": 55.57820121053438
                },
                "M16": {
                    "idx": "M16",
                    "quay_crane_id": "QC1",
                    "yard_block_loc": [
                        "B2",
                        24,
                        1
                    ],
                    "yard_crane_process_time": 25.291852874650267,
                    "locked": true,
                    "release_time": 1800,
                    "vehicle_speed": 1.435,
                    "station_process_time": 90.32373113350138,
                    "intersection_process_time": 32.59599658119555
                },
                "M17": {
                    "idx": "M17",
                    "quay_crane_id": "QC1",
                    "yard_block_loc": [
                        "A4",
                        26,
                        3
                    ],
                    "yard_crane_process_time": 28.831251562279718,
                    "locked": true,
                    "release_time": 1920,
                    "vehicle_speed": 1.435,
                    "station_process_time": 101.03909279630857,
                    "intersection_process_time": 34.0395457929107
                },
                "M18": {
                    "idx": "M18",
                    "quay_crane_id": "QC1",
                    "yard_block_loc": [
                        "B1",
                        15,
                        3
                    ],
                    "yard_crane_process_time": 32.710683226018254,
                    "locked": true,
                    "release_time": 2040,
                    "vehicle_speed": 1.435,
                    "station_process_time": 116.85137467217427,
                    "intersection_process_time": 23.815636175586196
                },
                "M19": {
                    "idx": "M19",
                    "quay_crane_id": "QC1",
                    "yard_block_loc": [
                        "B1",
                        9,
                        1
                    ],
                    "yard_crane_process_time": 33.44061425959228,
                    "locked": true,
                    "release_time": 2160,
                    "vehicle_speed": 1.435,
                    "station_process_time": 148.381833839005,
                    "intersection_process_time": 27.088572456379808
                },
                "M20": {
                    "idx": "M20",
                    "quay_crane_id": "QC1",
                    "yard_block_loc": [
                        "C3",
                        11,
                        1
                    ],
                    "yard_crane_process_time": 25.029962011524887,
                    "locked": true,
                    "release_time": 2280,
                    "vehicle_speed": 1.435,
                    "station_process_time": 108.77420182867061,
                    "intersection_process_time": 52.52081594940019
                }
            },
            "location": [
                320,
                0
            ]
        },
        {
            "idx": "QC2",
            "missions": {
                "M21": {
                    "idx": "M21",
                    "quay_crane_id": "QC2",
                    "yard_block_loc": [
                        "C3",
                        19,
                        0
                    ],
                    "yard_crane_process_time": 30.584576961177973,
                    "locked": true,
                    "release_time": 0,
                    "vehicle_speed": 1.435,
                    "station_process_time": 120.21401270277197,
                    "intersection_process_time": 51.26975081086107
                },
                "M22": {
                    "idx": "M22",
                    "quay_crane_id": "QC2",
                    "yard_block_loc": [
                        "A3",
                        25,
                        3
                    ],
                    "yard_crane_process_time": 34.72621753853504,
                    "locked": true,
                    "release_time": 120,
                    "vehicle_speed": 1.435,
                    "station_process_time": 145.25258618335795,
                    "intersection_process_time": 50.25091829059125
                },
                "M23": {
                    "idx": "M23",
                    "quay_crane_id": "QC2",
                    "yard_block_loc": [
                        "B1",
                        8,
                        1
                    ],
                    "yard_crane_process_time": 25.143519829668016,
                    "locked": true,
                    "release_time": 240,
                    "vehicle_speed": 1.435,
                    "station_process_time": 117.06341258530585,
                    "intersection_process_time": 26.69282388177801
                },
                "M24": {
                    "idx": "M24",
                    "quay_crane_id": "QC2",
                    "yard_block_loc": [
                        "C3",
                        17,
                        0
                    ],
                    "yard_crane_process_time": 26.15376672973818,
                    "locked": true,
                    "release_time": 360,
                    "vehicle_speed": 1.435,
                    "station_process_time": 120.99121229676669,
                    "intersection_process_time": 22.090719283953145
                },
                "M25": {
                    "idx": "M25",
                    "quay_crane_id": "QC2",
                    "yard_block_loc": [
                        "C4",
                        3,
                        5
                    ],
                    "yard_crane_process_time": 27.64482869339988,
                    "locked": true,
                    "release_time": 480,
                    "vehicle_speed": 1.435,
                    "station_process_time": 105.28398620347362,
                    "intersection_process_time": 28.99057273470676
                },
                "M26": {
                    "idx": "M26",
                    "quay_crane_id": "QC2",
                    "yard_block_loc": [
                        "A4",
                        29,
                        7
                    ],
                    "yard_crane_process_time": 32.07771441540732,
                    "locked": true,
                    "release_time": 600,
                    "vehicle_speed": 1.435,
                    "station_process_time": 91.20348981426022,
                    "intersection_process_time": 30.99804669977249
                },
                "M27": {
                    "idx": "M27",
                    "quay_crane_id": "QC2",
                    "yard_block_loc": [
                        "B1",
                        14,
                        6
                    ],
                    "yard_crane_process_time": 31.436012577568164,
                    "locked": true,
                    "release_time": 720,
                    "vehicle_speed": 1.435,
                    "station_process_time": 112.49830436053131,
                    "intersection_process_time": 53.73797458403808
                },
                "M28": {
                    "idx": "M28",
                    "quay_crane_id": "QC2",
                    "yard_block_loc": [
                        "B2",
                        14,
                        6
                    ],
                    "yard_crane_process_time": 30.369503884675467,
                    "locked": true,
                    "release_time": 840,
                    "vehicle_speed": 1.435,
                    "station_process_time": 110.88787894818205,
                    "intersection_process_time": 54.55137727827323
                },
                "M29": {
                    "idx": "M29",
                    "quay_crane_id": "QC2",
                    "yard_block_loc": [
                        "C3",
                        25,
                        5
                    ],
                    "yard_crane_process_time": 27.981274423554265,
                    "locked": true,
                    "release_time": 960,
                    "vehicle_speed": 1.435,
                    "station_process_time": 120.46025604598394,
                    "intersection_process_time": 31.18274801297057
                },
                "M30": {
                    "idx": "M30",
                    "quay_crane_id": "QC2",
                    "yard_block_loc": [
                        "A4",
                        9,
                        6
                    ],
                    "yard_crane_process_time": 33.47747120040849,
                    "locked": true,
                    "release_time": 1080,
                    "vehicle_speed": 1.435,
                    "station_process_time": 143.28924055883604,
                    "intersection_process_time": 42.03887043013524
                },
                "M31": {
                    "idx": "M31",
                    "quay_crane_id": "QC2",
                    "yard_block_loc": [
                        "A3",
                        4,
                        1
                    ],
                    "yard_crane_process_time": 32.893798902414225,
                    "locked": true,
                    "release_time": 1200,
                    "vehicle_speed": 1.435,
                    "station_process_time": 138.11241378157024,
                    "intersection_process_time": 34.88235705688764
                },
                "M32": {
                    "idx": "M32",
                    "quay_crane_id": "QC2",
                    "yard_block_loc": [
                        "B1",
                        23,
                        4
                    ],
                    "yard_crane_process_time": 32.51159971822517,
                    "locked": true,
                    "release_time": 1320,
                    "vehicle_speed": 1.435,
                    "station_process_time": 142.95456394538343,
                    "intersection_process_time": 54.94966850989921
                },
                "M33": {
                    "idx": "M33",
                    "quay_crane_id": "QC2",
                    "yard_block_loc": [
                        "A1",
                        23,
                        0
                    ],
                    "yard_crane_process_time": 29.03657864015452,
                    "locked": true,
                    "release_time": 1440,
                    "vehicle_speed": 1.435,
                    "station_process_time": 122.30173650639446,
                    "intersection_process_time": 29.377106905780167
                },
                "M34": {
                    "idx": "M34",
                    "quay_crane_id": "QC2",
                    "yard_block_loc": [
                        "C4",
                        9,
                        3
                    ],
                    "yard_crane_process_time": 27.929045165737328,
                    "locked": true,
                    "release_time": 1560,
                    "vehicle_speed": 1.435,
                    "station_process_time": 104.21729538105633,
                    "intersection_process_time": 31.80960813749671
                },
                "M35": {
                    "idx": "M35",
                    "quay_crane_id": "QC2",
                    "yard_block_loc": [
                        "B1",
                        23,
                        6
                    ],
                    "yard_crane_process_time": 33.86822973505994,
                    "locked": true,
                    "release_time": 1680,
                    "vehicle_speed": 1.435,
                    "station_process_time": 115.26108220550472,
                    "intersection_process_time": 30.041302939116918
                },
                "M36": {
                    "idx": "M36",
                    "quay_crane_id": "QC2",
                    "yard_block_loc": [
                        "B1",
                        24,
                        7
                    ],
                    "yard_crane_process_time": 30.18308987173457,
                    "locked": true,
                    "release_time": 1800,
                    "vehicle_speed": 1.435,
                    "station_process_time": 107.52225362862669,
                    "intersection_process_time": 59.249999630211214
                },
                "M37": {
                    "idx": "M37",
                    "quay_crane_id": "QC2",
                    "yard_block_loc": [
                        "B1",
                        18,
                        1
                    ],
                    "yard_crane_process_time": 26.989971045537665,
                    "locked": true,
                    "release_time": 1920,
                    "vehicle_speed": 1.435,
                    "station_process_time": 108.4220592095557,
                    "intersection_process_time": 31.952917158700238
                },
                "M38": {
                    "idx": "M38",
                    "quay_crane_id": "QC2",
                    "yard_block_loc": [
                        "B2",
                        8,
                        6
                    ],
                    "yard_crane_process_time": 26.369996787731363,
                    "locked": true,
                    "release_time": 2040,
                    "vehicle_speed": 1.435,
                    "station_process_time": 117.97007656296839,
                    "intersection_process_time": 27.36074913456993
                },
                "M39": {
                    "idx": "M39",
                    "quay_crane_id": "QC2",
                    "yard_block_loc": [
                        "C3",
                        28,
                        5
                    ],
                    "yard_crane_process_time": 34.13584108121168,
                    "locked": true,
                    "release_time": 2160,
                    "vehicle_speed": 1.435,
                    "station_process_time": 99.66787190076177,
                    "intersection_process_time": 37.20424395900186
                },
                "M40": {
                    "idx": "M40",
                    "quay_crane_id": "QC2",
                    "yard_block_loc": [
                        "B2",
                        20,
                        0
                    ],
                    "yard_crane_process_time": 33.4798081003211,
                    "locked": true,
                    "release_time": 2280,
                    "vehicle_speed": 1.435,
                    "station_process_time": 99.1618509657612,
                    "intersection_process_time": 20.95607951544592
                }
            },
            "location": [
                365,
                0
            ]
        },
        {
            "idx": "QC3",
            "missions": {
                "M41": {
                    "idx": "M41",
                    "quay_crane_id": "QC3",
                    "yard_block_loc": [
                        "C3",
                        8,
                        4
                    ],
                    "yard_crane_process_time": 34.8218732203956,
                    "locked": true,
                    "release_time": 0,
                    "vehicle_speed": 1.435,
                    "station_process_time": 143.2226518427275,
                    "intersection_process_time": 50.08803227904114
                },
                "M42": {
                    "idx": "M42",
                    "quay_crane_id": "QC3",
                    "yard_block_loc": [
                        "B1",
                        0,
                        3
                    ],
                    "yard_crane_process_time": 27.503991423505674,
                    "locked": true,
                    "release_time": 120,
                    "vehicle_speed": 1.435,
                    "station_process_time": 135.81263812923066,
                    "intersection_process_time": 45.1460037407583
                },
                "M43": {
                    "idx": "M43",
                    "quay_crane_id": "QC3",
                    "yard_block_loc": [
                        "A4",
                        27,
                        7
                    ],
                    "yard_crane_process_time": 27.92648059278339,
                    "locked": true,
                    "release_time": 240,
                    "vehicle_speed": 1.435,
                    "station_process_time": 92.12639968736622,
                    "intersection_process_time": 21.47269805558285
                },
                "M44": {
                    "idx": "M44",
                    "quay_crane_id": "QC3",
                    "yard_block_loc": [
                        "A3",
                        27,
                        6
                    ],
                    "yard_crane_process_time": 34.24326480204376,
                    "locked": true,
                    "release_time": 360,
                    "vehicle_speed": 1.435,
                    "station_process_time": 144.25562703494214,
                    "intersection_process_time": 53.49368494726984
                },
                "M45": {
                    "idx": "M45",
                    "quay_crane_id": "QC3",
                    "yard_block_loc": [
                        "A4",
                        20,
                        7
                    ],
                    "yard_crane_process_time": 28.801204215087132,
                    "locked": true,
                    "release_time": 480,
                    "vehicle_speed": 1.435,
                    "station_process_time": 120.30384836438044,
                    "intersection_process_time": 59.266226943001634
                },
                "M46": {
                    "idx": "M46",
                    "quay_crane_id": "QC3",
                    "yard_block_loc": [
                        "A3",
                        10,
                        6
                    ],
                    "yard_crane_process_time": 32.30591104120565,
                    "locked": true,
                    "release_time": 600,
                    "vehicle_speed": 1.435,
                    "station_process_time": 123.43981813573019,
                    "intersection_process_time": 52.74896586473579
                },
                "M47": {
                    "idx": "M47",
                    "quay_crane_id": "QC3",
                    "yard_block_loc": [
                        "A4",
                        10,
                        4
                    ],
                    "yard_crane_process_time": 34.99894088852696,
                    "locked": true,
                    "release_time": 720,
                    "vehicle_speed": 1.435,
                    "station_process_time": 124.8931700917923,
                    "intersection_process_time": 27.99685498788599
                },
                "M48": {
                    "idx": "M48",
                    "quay_crane_id": "QC3",
                    "yard_block_loc": [
                        "A4",
                        25,
                        1
                    ],
                    "yard_crane_process_time": 33.51520439586082,
                    "locked": true,
                    "release_time": 840,
                    "vehicle_speed": 1.435,
                    "station_process_time": 148.15139853217508,
                    "intersection_process_time": 34.57337524068629
                },
                "M49": {
                    "idx": "M49",
                    "quay_crane_id": "QC3",
                    "yard_block_loc": [
                        "B2",
                        29,
                        6
                    ],
                    "yard_crane_process_time": 33.90023384947135,
                    "locked": true,
                    "release_time": 960,
                    "vehicle_speed": 1.435,
                    "station_process_time": 114.34580079447831,
                    "intersection_process_time": 49.00324142459952
                },
                "M50": {
                    "idx": "M50",
                    "quay_crane_id": "QC3",
                    "yard_block_loc": [
                        "A1",
                        2,
                        6
                    ],
                    "yard_crane_process_time": 27.068072806588887,
                    "locked": true,
                    "release_time": 1080,
                    "vehicle_speed": 1.435,
                    "station_process_time": 149.81082820265348,
                    "intersection_process_time": 36.273321973163526
                },
                "M51": {
                    "idx": "M51",
                    "quay_crane_id": "QC3",
                    "yard_block_loc": [
                        "C3",
                        26,
                        2
                    ],
                    "yard_crane_process_time": 33.163444197098656,
                    "locked": true,
                    "release_time": 1200,
                    "vehicle_speed": 1.435,
                    "station_process_time": 112.77915843761495,
                    "intersection_process_time": 23.97200538186421
                },
                "M52": {
                    "idx": "M52",
                    "quay_crane_id": "QC3",
                    "yard_block_loc": [
                        "B1",
                        26,
                        7
                    ],
                    "yard_crane_process_time": 33.59375316938824,
                    "locked": true,
                    "release_time": 1320,
                    "vehicle_speed": 1.435,
                    "station_process_time": 113.12293955219948,
                    "intersection_process_time": 23.147456984620874
                },
                "M53": {
                    "idx": "M53",
                    "quay_crane_id": "QC3",
                    "yard_block_loc": [
                        "A1",
                        2,
                        2
                    ],
                    "yard_crane_process_time": 33.75260795681169,
                    "locked": true,
                    "release_time": 1440,
                    "vehicle_speed": 1.435,
                    "station_process_time": 117.44266292558878,
                    "intersection_process_time": 29.037808425752356
                },
                "M54": {
                    "idx": "M54",
                    "quay_crane_id": "QC3",
                    "yard_block_loc": [
                        "A4",
                        18,
                        3
                    ],
                    "yard_crane_process_time": 34.81420069325317,
                    "locked": true,
                    "release_time": 1560,
                    "vehicle_speed": 1.435,
                    "station_process_time": 97.86296033821338,
                    "intersection_process_time": 21.269647560193548
                },
                "M55": {
                    "idx": "M55",
                    "quay_crane_id": "QC3",
                    "yard_block_loc": [
                        "C4",
                        13,
                        5
                    ],
                    "yard_crane_process_time": 27.860922685314517,
                    "locked": true,
                    "release_time": 1680,
                    "vehicle_speed": 1.435,
                    "station_process_time": 119.3031979049843,
                    "intersection_process_time": 33.13327663060234
                },
                "M56": {
                    "idx": "M56",
                    "quay_crane_id": "QC3",
                    "yard_block_loc": [
                        "B1",
                        12,
                        6
                    ],
                    "yard_crane_process_time": 27.2758552676738,
                    "locked": true,
                    "release_time": 1800,
                    "vehicle_speed": 1.435,
                    "station_process_time": 119.75967761063986,
                    "intersection_process_time": 52.76170412320692
                },
                "M57": {
                    "idx": "M57",
                    "quay_crane_id": "QC3",
                    "yard_block_loc": [
                        "A4",
                        23,
                        7
                    ],
                    "yard_crane_process_time": 26.76629715439005,
                    "locked": true,
                    "release_time": 1920,
                    "vehicle_speed": 1.435,
                    "station_process_time": 105.47142309183282,
                    "intersection_process_time": 52.2843364971375
                },
                "M58": {
                    "idx": "M58",
                    "quay_crane_id": "QC3",
                    "yard_block_loc": [
                        "A1",
                        5,
                        6
                    ],
                    "yard_crane_process_time": 26.267602866482232,
                    "locked": true,
                    "release_time": 2040,
                    "vehicle_speed": 1.435,
                    "station_process_time": 115.61897807584464,
                    "intersection_process_time": 54.64098753738159
                },
                "M59": {
                    "idx": "M59",
                    "quay_crane_id": "QC3",
                    "yard_block_loc": [
                        "A4",
                        16,
                        0
                    ],
                    "yard_crane_process_time": 31.2687036247279,
                    "locked": true,
                    "release_time": 2160,
                    "vehicle_speed": 1.435,
                    "station_process_time": 140.98268372435763,
                    "intersection_process_time": 28.045599725460523
                },
                "M60": {
                    "idx": "M60",
                    "quay_crane_id": "QC3",
                    "yard_block_loc": [
                        "C4",
                        8,
                        4
                    ],
                    "yard_crane_process_time": 33.488530942112874,
                    "locked": true,
                    "release_time": 2280,
                    "vehicle_speed": 1.435,
                    "station_process_time": 138.35354958403246,
                    "intersection_process_time": 56.86603785710916
                }
            },
            "location": [
                410,
                0
            ]
        },
        {
            "idx": "QC4",
            "missions": {
                "M61": {
                    "idx": "M61",
                    "quay_crane_id": "QC4",
                    "yard_block_loc": [
                        "A4",
                        13,
                        6
                    ],
                    "yard_crane_process_time": 33.825426944704496,
                    "locked": true,
                    "release_time": 0,
                    "vehicle_speed": 1.435,
                    "station_process_time": 126.78447289444196,
                    "intersection_process_time": 27.53452227960155
                },
                "M62": {
                    "idx": "M62",
                    "quay_crane_id": "QC4",
                    "yard_block_loc": [
                        "C4",
                        13,
                        1
                    ],
                    "yard_crane_process_time": 29.999418993099813,
                    "locked": true,
                    "release_time": 120,
                    "vehicle_speed": 1.435,
                    "station_process_time": 148.42484190203723,
                    "intersection_process_time": 23.082614767104218
                },
                "M63": {
                    "idx": "M63",
                    "quay_crane_id": "QC4",
                    "yard_block_loc": [
                        "B2",
                        20,
                        6
                    ],
                    "yard_crane_process_time": 30.46300140378282,
                    "locked": true,
                    "release_time": 240,
                    "vehicle_speed": 1.435,
                    "station_process_time": 142.87136835856774,
                    "intersection_process_time": 24.807578504032655
                },
                "M64": {
                    "idx": "M64",
                    "quay_crane_id": "QC4",
                    "yard_block_loc": [
                        "A1",
                        20,
                        6
                    ],
                    "yard_crane_process_time": 26.391024972333213,
                    "locked": true,
                    "release_time": 360,
                    "vehicle_speed": 1.435,
                    "station_process_time": 124.78804368708705,
                    "intersection_process_time": 46.0753689936869
                },
                "M65": {
                    "idx": "M65",
                    "quay_crane_id": "QC4",
                    "yard_block_loc": [
                        "B2",
                        24,
                        4
                    ],
                    "yard_crane_process_time": 28.845196538414463,
                    "locked": true,
                    "release_time": 480,
                    "vehicle_speed": 1.435,
                    "station_process_time": 103.90335458305,
                    "intersection_process_time": 59.12565164600222
                },
                "M66": {
                    "idx": "M66",
                    "quay_crane_id": "QC4",
                    "yard_block_loc": [
                        "A3",
                        25,
                        2
                    ],
                    "yard_crane_process_time": 26.34950189959615,
                    "locked": true,
                    "release_time": 600,
                    "vehicle_speed": 1.435,
                    "station_process_time": 116.66550508075892,
                    "intersection_process_time": 36.82919977871938
                },
                "M67": {
                    "idx": "M67",
                    "quay_crane_id": "QC4",
                    "yard_block_loc": [
                        "A1",
                        21,
                        4
                    ],
                    "yard_crane_process_time": 29.318623151415537,
                    "locked": true,
                    "release_time": 720,
                    "vehicle_speed": 1.435,
                    "station_process_time": 96.3884121088666,
                    "intersection_process_time": 38.91998232845043
                },
                "M68": {
                    "idx": "M68",
                    "quay_crane_id": "QC4",
                    "yard_block_loc": [
                        "C4",
                        7,
                        7
                    ],
                    "yard_crane_process_time": 28.024329537456325,
                    "locked": true,
                    "release_time": 840,
                    "vehicle_speed": 1.435,
                    "station_process_time": 140.13014464152536,
                    "intersection_process_time": 38.51409041895852
                },
                "M69": {
                    "idx": "M69",
                    "quay_crane_id": "QC4",
                    "yard_block_loc": [
                        "A4",
                        4,
                        1
                    ],
                    "yard_crane_process_time": 32.69543091306247,
                    "locked": true,
                    "release_time": 960,
                    "vehicle_speed": 1.435,
                    "station_process_time": 138.28744581193092,
                    "intersection_process_time": 27.08806885558895
                },
                "M70": {
                    "idx": "M70",
                    "quay_crane_id": "QC4",
                    "yard_block_loc": [
                        "B2",
                        3,
                        0
                    ],
                    "yard_crane_process_time": 34.56217893201105,
                    "locked": true,
                    "release_time": 1080,
                    "vehicle_speed": 1.435,
                    "station_process_time": 122.88563334364065,
                    "intersection_process_time": 48.70789985380202
                },
                "M71": {
                    "idx": "M71",
                    "quay_crane_id": "QC4",
                    "yard_block_loc": [
                        "C4",
                        4,
                        5
                    ],
                    "yard_crane_process_time": 34.155799697444934,
                    "locked": true,
                    "release_time": 1200,
                    "vehicle_speed": 1.435,
                    "station_process_time": 106.43537592698013,
                    "intersection_process_time": 20.272608112941406
                },
                "M72": {
                    "idx": "M72",
                    "quay_crane_id": "QC4",
                    "yard_block_loc": [
                        "B1",
                        15,
                        7
                    ],
                    "yard_crane_process_time": 25.06299220819618,
                    "locked": true,
                    "release_time": 1320,
                    "vehicle_speed": 1.435,
                    "station_process_time": 93.14275951100585,
                    "intersection_process_time": 49.05967229183714
                },
                "M73": {
                    "idx": "M73",
                    "quay_crane_id": "QC4",
                    "yard_block_loc": [
                        "B2",
                        15,
                        7
                    ],
                    "yard_crane_process_time": 33.62943600983077,
                    "locked": true,
                    "release_time": 1440,
                    "vehicle_speed": 1.435,
                    "station_process_time": 113.61212796815967,
                    "intersection_process_time": 53.69193766624192
                },
                "M74": {
                    "idx": "M74",
                    "quay_crane_id": "QC4",
                    "yard_block_loc": [
                        "C3",
                        14,
                        3
                    ],
                    "yard_crane_process_time": 33.64566782671913,
                    "locked": true,
                    "release_time": 1560,
                    "vehicle_speed": 1.435,
                    "station_process_time": 148.25179929355537,
                    "intersection_process_time": 55.94845691319702
                },
                "M75": {
                    "idx": "M75",
                    "quay_crane_id": "QC4",
                    "yard_block_loc": [
                        "B2",
                        5,
                        7
                    ],
                    "yard_crane_process_time": 25.771937198767784,
                    "locked": true,
                    "release_time": 1680,
                    "vehicle_speed": 1.435,
                    "station_process_time": 120.98376354269988,
                    "intersection_process_time": 20.981095306087077
                },
                "M76": {
                    "idx": "M76",
                    "quay_crane_id": "QC4",
                    "yard_block_loc": [
                        "C3",
                        23,
                        1
                    ],
                    "yard_crane_process_time": 32.00730777673061,
                    "locked": true,
                    "release_time": 1800,
                    "vehicle_speed": 1.435,
                    "station_process_time": 112.88813374623581,
                    "intersection_process_time": 40.59843734411935
                },
                "M77": {
                    "idx": "M77",
                    "quay_crane_id": "QC4",
                    "yard_block_loc": [
                        "B1",
                        25,
                        2
                    ],
                    "yard_crane_process_time": 31.094828147944362,
                    "locked": true,
                    "release_time": 1920,
                    "vehicle_speed": 1.435,
                    "station_process_time": 111.07798546066583,
                    "intersection_process_time": 56.13919476900798
                },
                "M78": {
                    "idx": "M78",
                    "quay_crane_id": "QC4",
                    "yard_block_loc": [
                        "C4",
                        28,
                        4
                    ],
                    "yard_crane_process_time": 28.2602660387742,
                    "locked": true,
                    "release_time": 2040,
                    "vehicle_speed": 1.435,
                    "station_process_time": 110.2049114787061,
                    "intersection_process_time": 23.897917889755334
                },
                "M79": {
                    "idx": "M79",
                    "quay_crane_id": "QC4",
                    "yard_block_loc": [
                        "A4",
                        17,
                        1
                    ],
                    "yard_crane_process_time": 29.444326801235402,
                    "locked": true,
                    "release_time": 2160,
                    "vehicle_speed": 1.435,
                    "station_process_time": 147.16077889972186,
                    "intersection_process_time": 39.63973275889901
                },
                "M80": {
                    "idx": "M80",
                    "quay_crane_id": "QC4",
                    "yard_block_loc": [
                        "A4",
                        17,
                        2
                    ],
                    "yard_crane_process_time": 34.79439398276057,
                    "locked": true,
                    "release_time": 2280,
                    "vehicle_speed": 1.435,
                    "station_process_time": 142.04858255845102,
                    "intersection_process_time": 32.55435460830988
                }
            },
            "location": [
                455,
                0
            ]
        },
        {
            "idx": "QC5",
            "missions": {
                "M81": {
                    "idx": "M81",
                    "quay_crane_id": "QC5",
                    "yard_block_loc": [
                        "C3",
                        23,
                        0
                    ],
                    "yard_crane_process_time": 27.015074021279872,
                    "locked": true,
                    "release_time": 0,
                    "vehicle_speed": 1.435,
                    "station_process_time": 133.55881870613922,
                    "intersection_process_time": 31.274521182753958
                },
                "M82": {
                    "idx": "M82",
                    "quay_crane_id": "QC5",
                    "yard_block_loc": [
                        "C4",
                        11,
                        6
                    ],
                    "yard_crane_process_time": 28.795173425551376,
                    "locked": true,
                    "release_time": 120,
                    "vehicle_speed": 1.435,
                    "station_process_time": 98.95670012920463,
                    "intersection_process_time": 33.703141278288804
                },
                "M83": {
                    "idx": "M83",
                    "quay_crane_id": "QC5",
                    "yard_block_loc": [
                        "A1",
                        1,
                        4
                    ],
                    "yard_crane_process_time": 26.72447396804977,
                    "locked": true,
                    "release_time": 240,
                    "vehicle_speed": 1.435,
                    "station_process_time": 123.37452387910834,
                    "intersection_process_time": 37.7526376288376
                },
                "M84": {
                    "idx": "M84",
                    "quay_crane_id": "QC5",
                    "yard_block_loc": [
                        "C4",
                        28,
                        0
                    ],
                    "yard_crane_process_time": 31.888015979055236,
                    "locked": true,
                    "release_time": 360,
                    "vehicle_speed": 1.435,
                    "station_process_time": 114.1357002228611,
                    "intersection_process_time": 37.75448826064391
                },
                "M85": {
                    "idx": "M85",
                    "quay_crane_id": "QC5",
                    "yard_block_loc": [
                        "B2",
                        21,
                        4
                    ],
                    "yard_crane_process_time": 29.228264346134292,
                    "locked": true,
                    "release_time": 480,
                    "vehicle_speed": 1.435,
                    "station_process_time": 142.6787791298571,
                    "intersection_process_time": 43.06546082844001
                },
                "M86": {
                    "idx": "M86",
                    "quay_crane_id": "QC5",
                    "yard_block_loc": [
                        "B2",
                        14,
                        1
                    ],
                    "yard_crane_process_time": 32.17575299371462,
                    "locked": true,
                    "release_time": 600,
                    "vehicle_speed": 1.435,
                    "station_process_time": 133.7761029513199,
                    "intersection_process_time": 43.930656040049385
                },
                "M87": {
                    "idx": "M87",
                    "quay_crane_id": "QC5",
                    "yard_block_loc": [
                        "B2",
                        27,
                        5
                    ],
                    "yard_crane_process_time": 26.80446923040551,
                    "locked": true,
                    "release_time": 720,
                    "vehicle_speed": 1.435,
                    "station_process_time": 118.2220638304076,
                    "intersection_process_time": 50.85279574667354
                },
                "M88": {
                    "idx": "M88",
                    "quay_crane_id": "QC5",
                    "yard_block_loc": [
                        "B2",
                        4,
                        0
                    ],
                    "yard_crane_process_time": 32.791207411848234,
                    "locked": true,
                    "release_time": 840,
                    "vehicle_speed": 1.435,
                    "station_process_time": 99.63978850224083,
                    "intersection_process_time": 43.68765437229726
                },
                "M89": {
                    "idx": "M89",
                    "quay_crane_id": "QC5",
                    "yard_block_loc": [
                        "A1",
                        7,
                        3
                    ],
                    "yard_crane_process_time": 32.29265785434265,
                    "locked": true,
                    "release_time": 960,
                    "vehicle_speed": 1.435,
                    "station_process_time": 131.1767927044409,
                    "intersection_process_time": 55.78416513206575
                },
                "M90": {
                    "idx": "M90",
                    "quay_crane_id": "QC5",
                    "yard_block_loc": [
                        "C3",
                        3,
                        3
                    ],
                    "yard_crane_process_time": 29.319980741121086,
                    "locked": true,
                    "release_time": 1080,
                    "vehicle_speed": 1.435,
                    "station_process_time": 115.63297623974074,
                    "intersection_process_time": 57.20374329225073
                },
                "M91": {
                    "idx": "M91",
                    "quay_crane_id": "QC5",
                    "yard_block_loc": [
                        "A1",
                        18,
                        0
                    ],
                    "yard_crane_process_time": 26.21929444727264,
                    "locked": true,
                    "release_time": 1200,
                    "vehicle_speed": 1.435,
                    "station_process_time": 138.17911400531537,
                    "intersection_process_time": 46.58082566244651
                },
                "M92": {
                    "idx": "M92",
                    "quay_crane_id": "QC5",
                    "yard_block_loc": [
                        "A1",
                        6,
                        4
                    ],
                    "yard_crane_process_time": 32.4156494080581,
                    "locked": true,
                    "release_time": 1320,
                    "vehicle_speed": 1.435,
                    "station_process_time": 147.30115385747646,
                    "intersection_process_time": 46.35446977853438
                },
                "M93": {
                    "idx": "M93",
                    "quay_crane_id": "QC5",
                    "yard_block_loc": [
                        "A3",
                        5,
                        6
                    ],
                    "yard_crane_process_time": 34.906348019077434,
                    "locked": true,
                    "release_time": 1440,
                    "vehicle_speed": 1.435,
                    "station_process_time": 122.25435799966797,
                    "intersection_process_time": 56.5843165166842
                },
                "M94": {
                    "idx": "M94",
                    "quay_crane_id": "QC5",
                    "yard_block_loc": [
                        "B2",
                        0,
                        2
                    ],
                    "yard_crane_process_time": 27.454639640079964,
                    "locked": true,
                    "release_time": 1560,
                    "vehicle_speed": 1.435,
                    "station_process_time": 121.6760571984506,
                    "intersection_process_time": 28.69190888257776
                },
                "M95": {
                    "idx": "M95",
                    "quay_crane_id": "QC5",
                    "yard_block_loc": [
                        "C3",
                        23,
                        2
                    ],
                    "yard_crane_process_time": 27.764555882588603,
                    "locked": true,
                    "release_time": 1680,
                    "vehicle_speed": 1.435,
                    "station_process_time": 94.6587944980337,
                    "intersection_process_time": 31.64712559066213
                },
                "M96": {
                    "idx": "M96",
                    "quay_crane_id": "QC5",
                    "yard_block_loc": [
                        "A4",
                        8,
                        4
                    ],
                    "yard_crane_process_time": 33.97380641960206,
                    "locked": true,
                    "release_time": 1800,
                    "vehicle_speed": 1.435,
                    "station_process_time": 115.21116631890307,
                    "intersection_process_time": 48.870049634754174
                },
                "M97": {
                    "idx": "M97",
                    "quay_crane_id": "QC5",
                    "yard_block_loc": [
                        "A3",
                        23,
                        0
                    ],
                    "yard_crane_process_time": 31.482567900810214,
                    "locked": true,
                    "release_time": 1920,
                    "vehicle_speed": 1.435,
                    "station_process_time": 142.94571744191683,
                    "intersection_process_time": 51.21817587470405
                },
                "M98": {
                    "idx": "M98",
                    "quay_crane_id": "QC5",
                    "yard_block_loc": [
                        "A3",
                        7,
                        0
                    ],
                    "yard_crane_process_time": 34.935487339908654,
                    "locked": true,
                    "release_time": 2040,
                    "vehicle_speed": 1.435,
                    "station_process_time": 120.83765200281938,
                    "intersection_process_time": 45.619501800885516
                },
                "M99": {
                    "idx": "M99",
                    "quay_crane_id": "QC5",
                    "yard_block_loc": [
                        "A4",
                        24,
                        3
                    ],
                    "yard_crane_process_time": 26.177075627416595,
                    "locked": true,
                    "release_time": 2160,
                    "vehicle_speed": 1.435,
                    "station_process_time": 136.6709258914951,
                    "intersection_process_time": 45.32750311858916
                },
                "M100": {
                    "idx": "M100",
                    "quay_crane_id": "QC5",
                    "yard_block_loc": [
                        "C4",
                        29,
                        4
                    ],
                    "yard_crane_process_time": 32.726906450259676,
                    "locked": true,
                    "release_time": 2280,
                    "vehicle_speed": 1.435,
                    "station_process_time": 147.28737933223292,
                    "intersection_process_time": 44.38819127903368
                }
            },
            "location": [
                500,
                0
            ]
        }
    ],
    "buffers": [
        {
            "idx": "BF1",
            "location": [
                320,
                0
            ],
            "handling_time": 60,
            "capacity": 5
        },
        {
            "idx": "BF2",
            "location": [
                365,
                0
            ],
            "handling_time": 60,
            "capacity": 5
        },
        {
            "idx": "BF3",
            "location": [
                410,
                0
            ],
            "handling_time": 60,
            "capacity": 5
        },
        {
            "idx": "BF4",
            "location": [
                455,
                0
            ],
            "handling_time": 60,
            "capacity": 5
        },
        {
            "idx": "BF5",
            "location": [
                500,
                0
            ],
            "handling_time": 60,
            "capacity": 5
        }
    ],
    "lock_stations": [
        {
            "idx": "S1",
            "location": [
                180,
                64
            ],
            "capacity": 5,
            "handling_time": 142.47786205364727,
            "lock_station_buffers": {
                "LS11": {
                    "idx": "LS1",
                    "location": [
                        30,
                        69
                    ],
                    "lock_station_idx": "S1",
                    "wait_time_delay": 0
                },
                "LS12": {
                    "idx": "LS2",
                    "location": [
                        30,
                        74
                    ],
                    "lock_station_idx": "S1",
                    "wait_time_delay": 0
                },
                "LS13": {
                    "idx": "LS3",
                    "location": [
                        30,
                        79
                    ],
                    "lock_station_idx": "S1",
                    "wait_time_delay": 0
                },
                "LS14": {
                    "idx": "LS4",
                    "location": [
                        30,
                        84
                    ],
                    "lock_station_idx": "S1",
                    "wait_time_delay": 0
                }
            }
        },
        {
            "idx": "S2",
            "location": [
                330,
                64
            ],
            "capacity": 5,
            "handling_time": 149.64179028909075,
            "lock_station_buffers": {
                "LS21": {
                    "idx": "LS1",
                    "location": [
                        180,
                        69
                    ],
                    "lock_station_idx": "S2",
                    "wait_time_delay": 0
                },
                "LS22": {
                    "idx": "LS2",
                    "location": [
                        180,
                        74
                    ],
                    "lock_station_idx": "S2",
                    "wait_time_delay": 0
                },
                "LS23": {
                    "idx": "LS3",
                    "location": [
                        180,
                        79
                    ],
                    "lock_station_idx": "S2",
                    "wait_time_delay": 0
                },
                "LS24": {
                    "idx": "LS4",
                    "location": [
                        180,
                        84
                    ],
                    "lock_station_idx": "S2",
                    "wait_time_delay": 0
                }
            }
        },
        {
            "idx": "S3",
            "location": [
                480,
                64
            ],
            "capacity": 5,
            "handling_time": 110.32096372751951,
            "lock_station_buffers": {
                "LS31": {
                    "idx": "LS1",
                    "location": [
                        330,
                        69
                    ],
                    "lock_station_idx": "S3",
                    "wait_time_delay": 0
                },
                "LS32": {
                    "idx": "LS2",
                    "location": [
                        330,
                        74
                    ],
                    "lock_station_idx": "S3",
                    "wait_time_delay": 0
                },
                "LS33": {
                    "idx": "LS3",
                    "location": [
                        330,
                        79
                    ],
                    "lock_station_idx": "S3",
                    "wait_time_delay": 0
                },
                "LS34": {
                    "idx": "LS4",
                    "location": [
                        330,
                        84
                    ],
                    "lock_station_idx": "S3",
                    "wait_time_delay": 0
                }
            }
        },
        {
            "idx": "S4",
            "location": [
                630,
                64
            ],
            "capacity": 5,
            "handling_time": 104.04130649258873,
            "lock_station_buffers": {
                "LS41": {
                    "idx": "LS1",
                    "location": [
                        480,
                        69
                    ],
                    "lock_station_idx": "S4",
                    "wait_time_delay": 0
                },
                "LS42": {
                    "idx": "LS2",
                    "location": [
                        480,
                        74
                    ],
                    "lock_station_idx": "S4",
                    "wait_time_delay": 0
                },
                "LS43": {
                    "idx": "LS3",
                    "location": [
                        480,
                        79
                    ],
                    "lock_station_idx": "S4",
                    "wait_time_delay": 0
                },
                "LS44": {
                    "idx": "LS4",
                    "location": [
                        480,
                        84
                    ],
                    "lock_station_idx": "S4",
                    "wait_time_delay": 0
                }
            }
        },
        {
            "idx": "S5",
            "location": [
                780,
                64
            ],
            "capacity": 5,
            "handling_time": 94.72066045401374,
            "lock_station_buffers": {
                "LS51": {
                    "idx": "LS1",
                    "location": [
                        630,
                        69
                    ],
                    "lock_station_idx": "S5",
                    "wait_time_delay": 0
                },
                "LS52": {
                    "idx": "LS2",
                    "location": [
                        630,
                        74
                    ],
                    "lock_station_idx": "S5",
                    "wait_time_delay": 0
                },
                "LS53": {
                    "idx": "LS3",
                    "location": [
                        630,
                        79
                    ],
                    "lock_station_idx": "S5",
                    "wait_time_delay": 0
                },
                "LS54": {
                    "idx": "LS4",
                    "location": [
                        630,
                        84
                    ],
                    "lock_station_idx": "S5",
                    "wait_time_delay": 0
                }
            }
        }
    ],
    "crossovers": [
        {
            "idx": "CO1",
            "location": [
                225.0,
                116.0
            ],
            "yard_block_list": [
                "A1",
                "A2",
                "A3",
                "A4"
            ]
        },
        {
            "idx": "CO2",
            "location": [
                460.0,
                116.0
            ],
            "yard_block_list": [
                "B1",
                "B2",
                "B3",
                "B4"
            ]
        },
        {
            "idx": "CO3",
            "location": [
                695.0,
                116.0
            ],
            "yard_block_list": [
                "C1",
                "C2",
                "C3",
                "C4"
            ]
        }
    ],
    "yard_blocks": [
        {
            "idx": "A1",
            "block_location": [
                20,
                128
            ]
        },
        {
            "idx": "A2",
            "block_location": [
                20.0,
                159.52
            ]
        },
        {
            "idx": "A3",
            "block_location": [
                20.0,
                191.04
            ]
        },
        {
            "idx": "A4",
            "block_location": [
                20.0,
                222.56
            ]
        },
        {
            "idx": "B1",
            "block_location": [
                255.0,
                128.0
            ]
        },
        {
            "idx": "B2",
            "block_location": [
                255.0,
                159.52
            ]
        },
        {
            "idx": "B3",
            "block_location": [
                255.0,
                191.04
            ]
        },
        {
            "idx": "B4",
            "block_location": [
                255.0,
                222.56
            ]
        },
        {
            "idx": "C1",
            "block_location": [
                490.0,
                128.0
            ]
        },
        {
            "idx": "C2",
            "block_location": [
                490.0,
                159.52
            ]
        },
        {
            "idx": "C3",
            "block_location": [
                490.0,
                191.04
            ]
        },
        {
            "idx": "C4",
            "block_location": [
                490.0,
                222.56
            ]
        }
    ],
    "yard_cranes": [
        {
            "idx": "YCA1",
            "block_id": "YCA1",
            "location": [
                0,
                8
            ],
            "x_move_rate": 2.17,
            "y_move_rate": 1.8,
            "handling_time": 27.51264607616754
        },
        {
            "idx": "YCA2",
            "block_id": "YCA2",
            "location": [
                0,
                8
            ],
            "x_move_rate": 2.17,
            "y_move_rate": 1.8,
            "handling_time": 31.603398868257926
        },
        {
            "idx": "YCA3",
            "block_id": "YCA3",
            "location": [
                0,
                8
            ],
            "x_move_rate": 2.17,
            "y_move_rate": 1.8,
            "handling_time": 28.049230898070856
        },
        {
            "idx": "YCA4",
            "block_id": "YCA4",
            "location": [
                0,
                8
            ],
            "x_move_rate": 2.17,
            "y_move_rate": 1.8,
            "handling_time": 25.005420449984584
        },
        {
            "idx": "YCB1",
            "block_id": "YCB1",
            "location": [
                0,
                8
            ],
            "x_move_rate": 2.17,
            "y_move_rate": 1.8,
            "handling_time": 30.37489776282962
        },
        {
            "idx": "YCB2",
            "block_id": "YCB2",
            "location": [
                0,
                8
            ],
            "x_move_rate": 2.17,
            "y_move_rate": 1.8,
            "handling_time": 31.78945983371928
        },
        {
            "idx": "YCB3",
            "block_id": "YCB3",
            "location": [
                0,
                8
            ],
            "x_move_rate": 2.17,
            "y_move_rate": 1.8,
            "handling_time": 27.19220681627056
        },
        {
            "idx": "YCB4",
            "block_id": "YCB4",
            "location": [
                0,
                8
            ],
            "x_move_rate": 2.17,
            "y_move_rate": 1.8,
            "handling_time": 29.62424389546165
        },
        {
            "idx": "YCC1",
            "block_id": "YCC1",
            "location": [
                0,
                8
            ],
            "x_move_rate": 2.17,
            "y_move_rate": 1.8,
            "handling_time": 31.874877200315282
        },
        {
            "idx": "YCC2",
            "block_id": "YCC2",
            "location": [
                0,
                8
            ],
            "x_move_rate": 2.17,
            "y_move_rate": 1.8,
            "handling_time": 33.40442275482159
        },
        {
            "idx": "YCC3",
            "block_id": "YCC3",
            "location": [
                0,
                8
            ],
            "x_move_rate": 2.17,
            "y_move_rate": 1.8,
            "handling_time": 29.627810549333283
        },
        {
            "idx": "YCC4",
            "block_id": "YCC4",
            "location": [
                0,
                8
            ],
            "x_move_rate": 2.17,
            "y_move_rate": 1.8,
            "handling_time": 32.853307480112
        }
    ]
}